typsphinx/__init__.py
typsphinx/builder.py
typsphinx/pdf.py
typsphinx/template_engine.py
typsphinx/translator.py
typsphinx/writer.py
typsphinx/templates/base.typ
typsphinx-0.3.0.dist-info/licenses/LICENSE
typsphinx-0.3.0.dist-info/METADATA
typsphinx-0.3.0.dist-info/WHEEL
typsphinx-0.3.0.dist-info/entry_points.txt
typsphinx-0.3.0.dist-info/top_level.txt
typsphinx-0.3.0.dist-info/RECORD
