Metadata-Version: 2.4
Name: typsphinx
Version: 0.3.0
Summary: Sphinx extension for Typst output
Author-email: Sphinx Typst Contributors <noreply@example.com>
License-Expression: MIT
Project-URL: Homepage, https://github.com/YuSabo90002/typsphinx
Project-URL: Documentation, https://github.com/YuSabo90002/typsphinx#readme
Project-URL: Repository, https://github.com/YuSabo90002/typsphinx
Project-URL: Issues, https://github.com/YuSabo90002/typsphinx/issues
Keywords: sphinx,typst,documentation,pdf
Classifier: Development Status :: 4 - Beta
Classifier: Framework :: Sphinx :: Extension
Classifier: Intended Audience :: Developers
Classifier: Programming Language :: Python :: 3
Classifier: Programming Language :: Python :: 3.9
Classifier: Programming Language :: Python :: 3.10
Classifier: Programming Language :: Python :: 3.11
Classifier: Programming Language :: Python :: 3.12
Classifier: Topic :: Documentation :: Sphinx
Classifier: Topic :: Software Development :: Documentation
Requires-Python: >=3.9
License-File: LICENSE
Requires-Dist: sphinx>=5.0
Requires-Dist: docutils>=0.18
Requires-Dist: typst>=0.11.1
Provides-Extra: dev
Requires-Dist: pytest>=7.0; extra == "dev"
Requires-Dist: pytest-cov>=4.0; extra == "dev"
Requires-Dist: tox>=4.0; extra == "dev"
Requires-Dist: tox-uv>=1.0; extra == "dev"
Requires-Dist: black>=23.0; extra == "dev"
Requires-Dist: ruff>=0.1.0; extra == "dev"
Requires-Dist: mypy>=1.0; extra == "dev"
Requires-Dist: sphinx-testing>=1.0; extra == "dev"
Requires-Dist: pre-commit>=3.0; extra == "dev"
Requires-Dist: types-docutils>=0.18; extra == "dev"
Requires-Dist: twine>=5.0; extra == "dev"
Requires-Dist: build>=1.0; extra == "dev"
Provides-Extra: docs
Requires-Dist: sphinx-rtd-theme>=2.0; extra == "docs"
Requires-Dist: sphinx-autodoc-typehints>=1.0; extra == "docs"
Dynamic: license-file
